{"stats":{"minecraft:used":{"minecraft:oak_planks":1,"minecraft:birch_boat":1,"minecraft:crafting_table":2,"minecraft:oak_boat":1,"minecraft:potato":15},"minecraft:picked_up":{"minecraft:stripped_oak_log":5,"minecraft:birch_log":3,"minecraft:crafting_table":1,"minecraft:ladder":1,"minecraft:potato":55,"minecraft:sand":1,"minecraft:stripped_spruce_log":1,"minecraft:wheat_seeds":1},"minecraft:custom":{"minecraft:time_since_rest":2361,"minecraft:interact_with_smithing_table":1,"minecraft:sprint_one_cm":60721,"minecraft:damage_taken":505,"minecraft:walk_one_cm":73564,"minecraft:mob_kills":1,"minecraft:damage_dealt":240,"minecraft:swim_one_cm":24606,"minecraft:interact_with_crafting_table":2,"minecraft:fly_one_cm":101823,"minecraft:open_barrel":2,"minecraft:play_time":27535,"minecraft:deaths":2,"minecraft:sneak_time":15,"minecraft:walk_under_water_one_cm":9694,"minecraft:boat_one_cm":281857,"minecraft:jump":565,"minecraft:leave_game":1,"minecraft:walk_on_water_one_cm":14883,"minecraft:time_since_death":4235,"minecraft:sleep_in_bed":2,"minecraft:climb_one_cm":3334,"minecraft:total_world_time":27535,"minecraft:fall_one_cm":7735},"minecraft:killed_by":{"iceandfire:sea_serpent":1,"minecraft:skeleton":1},"minecraft:killed":{"iceandfire:ghost":1},"minecraft:crafted":{"minecraft:oak_boat":1,"minecraft:oak_planks":20,"minecraft:crafting_table":2,"minecraft:birch_boat":1,"minecraft:birch_planks":12},"minecraft:mined":{"minecraft:birch_log":3,"minecraft:birch_leaves":1,"minecraft:crafting_table":1,"minecraft:grass":7,"minecraft:potatoes":15,"minecraft:sand":1,"minecraft:sugar_cane":1}},"DataVersion":3465}